CHANGES.txt
MANIFEST.in
README.txt
requirements.txt
setup.py
docs/HISTORY.txt
wheelcms_spokes/__init__.py
wheelcms_spokes/admin.py
wheelcms_spokes/file.py
wheelcms_spokes/image.py
wheelcms_spokes/models.py
wheelcms_spokes/news.py
wheelcms_spokes/page.py
wheelcms_spokes.egg-info/PKG-INFO
wheelcms_spokes.egg-info/SOURCES.txt
wheelcms_spokes.egg-info/dependency_links.txt
wheelcms_spokes.egg-info/namespace_packages.txt
wheelcms_spokes.egg-info/not-zip-safe
wheelcms_spokes.egg-info/requires.txt
wheelcms_spokes.egg-info/top_level.txt
wheelcms_spokes/static/img/icons/file.png
wheelcms_spokes/static/img/icons/folder_page.png
wheelcms_spokes/static/img/icons/image.png
wheelcms_spokes/static/img/icons/news.png
wheelcms_spokes/static/img/icons/page.png
wheelcms_spokes/templates/wheelcms_spokes/file_detail.html
wheelcms_spokes/templates/wheelcms_spokes/file_view.html
wheelcms_spokes/templates/wheelcms_spokes/image_detail.html
wheelcms_spokes/templates/wheelcms_spokes/image_view.html
wheelcms_spokes/templates/wheelcms_spokes/news_view.html
wheelcms_spokes/templates/wheelcms_spokes/page_contents.html
wheelcms_spokes/templates/wheelcms_spokes/page_view.html
wheelcms_spokes/tests/__init__.py
wheelcms_spokes/tests/conftest.py
wheelcms_spokes/tests/test_file_image.py
wheelcms_spokes/tests/test_news.py
wheelcms_spokes/tests/test_page.py