Metadata-Version: 1.1
Name: wheelcms-spokes
Version: 0.9
Summary: WheelCMS content type implementation
Home-page: http://github.com/wheelcms/wheelcms_spokes
Author: Ivo van der Wijk
Author-email: wheelcms@in.m3r.nl
License: BSD
Platform: UNKNOWN
Classifier: Programming Language :: Python
